handy_algorithms/__init__.py
handy_algorithms/numbers.py
handy_algorithms/strings.py
handy_algorithms-0.1.0.dist-info/METADATA
handy_algorithms-0.1.0.dist-info/WHEEL
handy_algorithms-0.1.0.dist-info/RECORD
