Metadata-Version: 2.1
Name: handy-algorithms
Version: 0.1.0
Summary: 
Author: Your Name
Author-email: michu31@gmail.com
Requires-Python: >=3.12,<4.0
Classifier: Programming Language :: Python :: 3
Classifier: Programming Language :: Python :: 3.12
Requires-Dist: pytest (>=7.4.4,<8.0.0)
Requires-Dist: pytest-cov (>=4.1.0,<5.0.0)
